bookshelf_common/__init__.py
bookshelf_common/errors/__init__.py
bookshelf_common/errors/bad_request_error.py
bookshelf_common/errors/custom_error.py
bookshelf_common/errors/not_authorized_error.py
bookshelf_common/errors/not_found_error.py
bookshelf_common/errors/request_validation_error.py
bookshelf_common/events/__init__.py
bookshelf_common/events/base_connection.py
bookshelf_common/events/base_listener.py
bookshelf_common/events/base_publisher.py
bookshelf_common/events/objects/__init__.py
bookshelf_common/events/objects/book_exchange.py
bookshelf_common/events/objects/book_sold.py
bookshelf_common/events/objects/expiration_exchange.py
bookshelf_common/events/objects/moderation_exchange.py
bookshelf_common/events/objects/order_exchange.py
bookshelf_common/events/objects/payment_exchange.py
bookshelf_common/events/objects/queue_list.py
bookshelf_common/events/objects/user_exchange.py
bookshelf_common-0.0.9.1.dist-info/LICENSE
bookshelf_common-0.0.9.1.dist-info/METADATA
bookshelf_common-0.0.9.1.dist-info/WHEEL
bookshelf_common-0.0.9.1.dist-info/top_level.txt
bookshelf_common-0.0.9.1.dist-info/RECORD
