Metadata-Version: 2.1
Name: bookshelf_common
Version: 0.0.9.1
Summary: Share common code for bookshelf
Home-page: https://github.com/mmuric/bookshelf-common
Author: Marko Muric
Author-email: <atis.443@gmail.com>
License: MIT
Project-URL: Bug Tracker, https://github.com/mmuric/bookshelf-common/issues
License-File: LICENSE
Requires-Dist: pika
